alcpack/__init__.py
alcpack/alcscript.py
alcpack-1.1.1.dist-info/LICENSE
alcpack-1.1.1.dist-info/METADATA
alcpack-1.1.1.dist-info/WHEEL
alcpack-1.1.1.dist-info/top_level.txt
alcpack-1.1.1.dist-info/RECORD
