Metadata-Version: 2.1
Name: alcpack
Version: 1.1.1
Summary: Adaptive Local Complementation Package
Home-page: UNKNOWN
Author: Amit Kumar Pal
Author-email: amitsweb@gmail.com
License: Apache 2
Download-URL: https://github.com/amitkpal/alcpack/archive/master.zip
Keywords: network simple connected graph local complementation creation of an edge
Platform: UNKNOWN
Classifier: Programming Language :: Python :: 3.5
Classifier: Programming Language :: Python :: 3.6
Classifier: Programming Language :: Python :: 3.7
Classifier: License :: OSI Approved :: Apache Software License
Classifier: Operating System :: OS Independent
Requires-Dist: networkx
